zc.resourcelibrary-2.1.0-py3.7-nspkg.pth
zc/resourcelibrary/README.rst
zc/resourcelibrary/__init__.py
zc/resourcelibrary/configure.zcml
zc/resourcelibrary/ftesting.zcml
zc/resourcelibrary/meta.zcml
zc/resourcelibrary/publication.py
zc/resourcelibrary/resourcelibrary.py
zc/resourcelibrary/tal.py
zc/resourcelibrary/zcml.py
zc/resourcelibrary/tests/__init__.py
zc/resourcelibrary/tests/duplicate_declarations.rst
zc/resourcelibrary/tests/duplicate_declarations.zcml
zc/resourcelibrary/tests/duplicate_declarations_overrides.zcml
zc/resourcelibrary/tests/localsite.rst
zc/resourcelibrary/tests/test_template_1.pt
zc/resourcelibrary/tests/test_template_2.pt
zc/resourcelibrary/tests/test_template_3.pt
zc/resourcelibrary/tests/test_template_4.pt
zc/resourcelibrary/tests/test_template_5.pt
zc/resourcelibrary/tests/test_template_6.pt
zc/resourcelibrary/tests/test_template_7.pt
zc/resourcelibrary/tests/test_unit.py
zc/resourcelibrary/tests/tests.py
zc/resourcelibrary/tests/example/1.js
zc/resourcelibrary/tests/example/2.css
zc/resourcelibrary/tests/example/3.kss
zc/resourcelibrary/tests/example/my-lib/included.css
zc/resourcelibrary/tests/example/my-lib/included.js
zc/resourcelibrary/tests/example/my-lib/included.kss
zc.resourcelibrary-2.1.0.dist-info/LICENSE.txt
zc.resourcelibrary-2.1.0.dist-info/METADATA
zc.resourcelibrary-2.1.0.dist-info/WHEEL
zc.resourcelibrary-2.1.0.dist-info/namespace_packages.txt
zc.resourcelibrary-2.1.0.dist-info/top_level.txt
zc.resourcelibrary-2.1.0.dist-info/RECORD
