Metadata-Version: 2.1
Name: zc.resourcelibrary
Version: 2.1.0
Summary: Post-rendering Resource Inclusion
Home-page: http://github.com/zopefoundation/zc.resourcelibrary
Author: Zope Foundation and Contributors
Author-email: zope-dev@zope.org
License: ZPL 2.1
Keywords: zope3 resource javascript css inclusion
Platform: UNKNOWN
Classifier: Development Status :: 5 - Production/Stable
Classifier: Environment :: Web Environment
Classifier: Intended Audience :: Developers
Classifier: License :: OSI Approved :: Zope Public License
Classifier: Programming Language :: Python
Classifier: Programming Language :: Python
Classifier: Programming Language :: Python :: 2
Classifier: Programming Language :: Python :: 2.7
Classifier: Programming Language :: Python :: 3
Classifier: Programming Language :: Python :: 3.4
Classifier: Programming Language :: Python :: 3.5
Classifier: Programming Language :: Python :: 3.6
Classifier: Programming Language :: Python :: 3.7
Classifier: Programming Language :: Python :: Implementation :: CPython
Classifier: Programming Language :: Python :: Implementation :: PyPy
Classifier: Natural Language :: English
Classifier: Operating System :: OS Independent
Classifier: Topic :: Internet :: WWW/HTTP
Classifier: Framework :: Zope :: 3
Requires-Dist: setuptools
Requires-Dist: zope.browserpage
Requires-Dist: zope.browserresource
Requires-Dist: zope.component
Requires-Dist: zope.configuration
Requires-Dist: zope.interface
Requires-Dist: zope.publisher
Requires-Dist: zope.security
Requires-Dist: zope.site
Requires-Dist: zope.tales
Requires-Dist: zope.traversing
Provides-Extra: test
Requires-Dist: webtest; extra == 'test'
Requires-Dist: zope.app.appsetup (>=4.0.0); extra == 'test'
Requires-Dist: zope.app.basicskin (>=4.0.0); extra == 'test'
Requires-Dist: zope.app.http (>=4.0.1); extra == 'test'
Requires-Dist: zope.app.publication (>=4.2.1); extra == 'test'
Requires-Dist: zope.app.security (>=4.0.0); extra == 'test'
Requires-Dist: zope.app.wsgi (>=4.1.0); extra == 'test'
Requires-Dist: zope.pagetemplate; extra == 'test'
Requires-Dist: zope.principalregistry; extra == 'test'
Requires-Dist: zope.securitypolicy; extra == 'test'
Requires-Dist: zope.testbrowser; extra == 'test'
Requires-Dist: zope.testing; extra == 'test'
Requires-Dist: zope.testrunner; extra == 'test'
